med_multiply/__init__.py
med_multiply/multiplication.py
med_multiply-0.1.3.dist-info/METADATA
med_multiply-0.1.3.dist-info/WHEEL
med_multiply-0.1.3.dist-info/top_level.txt
med_multiply-0.1.3.dist-info/RECORD
